[
  {
    "nombre": "lentejas",
    "altura": 90
  },
  {
    "nombre": "Spaguethi",
    "altura": 230
  },
  {
    "nombre": "Hamburguesa",
    "altura": 60
  },
  {
    "nombre": "Sopa",
    "altura": 50
  },
  {
    "nombre": "Patatas Bravas",
    "altura": 150
  },
  {
    "nombre": "Croquetas",
    "altura": 200
  },
  {
    "nombre": "Ensalada",
    "altura": 70
  },
  {
    "nombre": " Arroz tres delicias",
    "altura": 80
  },
  {
    "nombre": "Frutti di mari",
    "altura": 100
  },
  {
    "nombre": "Lubina",
    "altura": 50
  }
]